magen_user-0.1a2.data/scripts/user_api.py
magen_user-0.1a2.dist-info/DESCRIPTION.rst
magen_user-0.1a2.dist-info/METADATA
magen_user-0.1a2.dist-info/RECORD
magen_user-0.1a2.dist-info/WHEEL
magen_user-0.1a2.dist-info/metadata.json
magen_user-0.1a2.dist-info/top_level.txt
magen_user_api/__init__.py
magen_user_api/config.py
magen_user_api/db.py
magen_user_api/user_api.py
magen_user_api/user_model.py
magen_user_api/static/css/bootstrap.css
magen_user_api/static/css/bootstrap.min.css
magen_user_api/static/css/starter-template.css
magen_user_api/static/images/magentitle.png
magen_user_api/static/images/registrationimg.png
magen_user_api/templates/email_confirmation.html
magen_user_api/templates/index.html
magen_user_api/templates/login.html
magen_user_api/templates/registration.html
