Metadata-Version: 2.0
Name: magen-user
Version: 0.1a2
Summary: Magen Gmail Client Package
Home-page: http://www.cisco.com
Author: Alena Lifar
Author-email: alifar@cisco.com
License: Apache
Platform: UNKNOWN
Classifier: Development Status :: 2 - Pre-Alpha
Classifier: Intended Audience :: Education
Classifier: Intended Audience :: Financial and Insurance Industry
Classifier: Intended Audience :: Healthcare Industry
Classifier: Intended Audience :: Legal Industry
Classifier: Topic :: Security
Classifier: License :: OSI Approved :: Apache Software License
Classifier: Programming Language :: Python :: 3.6
Requires-Dist: aniso8601 (>=1.2.1)
Requires-Dist: coverage (>=4.4.1)
Requires-Dist: flake8 (>=3.3.0)
Requires-Dist: pytest (>=3.1.3)
Requires-Dist: Sphinx (>=1.6.3)
Requires-Dist: wheel (>=0.30.0a0)
Requires-Dist: httplib2 (>=0.10)
Requires-Dist: Flask (>=0.12.2)
Requires-Dist: Flask-Cors (>=3.0)
Requires-Dist: Flask-Login (>=0.4.1)
Requires-Dist: Flask-WTF (>=0.14.2)
Requires-Dist: Flask-ReCaptcha (>=0.4itsdangerous>=0.24)
Requires-Dist: WTForms (>=2.1)
Requires-Dist: pymongo (>=3.4)
